MANIFEST.in
README.rst
setup.py
src/flask_project_templates/__init__.py
src/flask_project_templates/flasktemplates.py
src/flask_project_templates.egg-info/PKG-INFO
src/flask_project_templates.egg-info/SOURCES.txt
src/flask_project_templates.egg-info/dependency_links.txt
src/flask_project_templates.egg-info/entry_points.txt
src/flask_project_templates.egg-info/not-zip-safe
src/flask_project_templates.egg-info/requires.txt
src/flask_project_templates.egg-info/top_level.txt
src/flask_project_templates/templates/__init__.py
src/flask_project_templates/templates/flask_basic/__init__.py
src/flask_project_templates/templates/flask_basic/app.py_tmpl
src/flask_project_templates/templates/flask_basic/static/+project+.css
src/flask_project_templates/templates/flask_basic/static/+project+.js
src/flask_project_templates/templates/flask_basic/templates/base.html_tmpl
src/flask_project_templates/templates/flask_basic/templates/index.html
src/flask_project_templates/templates/flask_sqla/manage.py_tmpl
src/flask_project_templates/templates/flask_sqla/requirements.txt
src/flask_project_templates/templates/flask_sqla/+project+/__init__.py_tmpl
src/flask_project_templates/templates/flask_sqla/+project+/forms.py
src/flask_project_templates/templates/flask_sqla/+project+/models.py_tmpl
src/flask_project_templates/templates/flask_sqla/+project+/settings.py_tmpl
src/flask_project_templates/templates/flask_sqla/+project+/urls.py_tmpl
src/flask_project_templates/templates/flask_sqla/+project+/core/__init__.py
src/flask_project_templates/templates/flask_sqla/+project+/static/css/+project+.css
src/flask_project_templates/templates/flask_sqla/+project+/static/js/+project+.js
src/flask_project_templates/templates/flask_sqla/+project+/templates/base.html_tmpl
src/flask_project_templates/templates/flask_sqla/+project+/templates/index.html
src/flask_project_templates/templates/flask_sqla/+project+/templates/macros.html
src/flask_project_templates/templates/flask_sqla/+project+/tests/__init__.py
src/flask_project_templates/templates/flask_sqla/+project+/views/__init__.py
src/flask_project_templates/templates/flask_sqla/+project+/views/main.py